{
    "patches": [
        {
            "bug_type": "integer_overflow",
            "pc": 1282,
            "patch": [
                {
                    "delete": "",
                    "insert": "DUP2 DUP2 PUSH32_0xffffffffffffffffffffffffffffffffffffffffffffffffffffffffffffffff SUB LT ISZERO PUSH_jump_loc_1 JUMPI PUSH1_0x0 DUP1 REVERT JUMPDEST_jump_loc_1",
                    "insert_mode": "before",
                    "constructor": false
                }
            ]
        },
        {
            "bug_type": "integer_overflow",
            "pc": 1291,
            "patch": [
                {
                    "delete": "",
                    "insert": "DUP2 DUP2 PUSH32_0xffffffffffffffffffffffffffffffffffffffffffffffffffffffffffffffff SUB LT ISZERO PUSH_jump_loc_1 JUMPI PUSH1_0x0 DUP1 REVERT JUMPDEST_jump_loc_1",
                    "insert_mode": "before",
                    "constructor": false
                }
            ]
        }
    ],
    "control_flow_graph_recovery_time": 0.5511820316314697,
    "control_flow_graph_recovery": "100%",
    "original_deployment_size": "330 bytes",
    "patched_deployment_size": "330 bytes",
    "original_runtime_size": "1798 bytes",
    "patched_runtime_size": "1892 bytes",
    "execution_time": 1.1473824977874756
}